Metadata-Version: 2.1
Name: pixaiAPI
Version: 0.1.11
Summary: An unofficial API for pixai.art for Python
Home-page: https://github.com/shidktbw/pixaiAPI
Author: shidktbw
Classifier: Programming Language :: Python :: 3.10
Classifier: License :: OSI Approved :: MIT License
